optimistix/__init__.py
optimistix/_ad.py
optimistix/_adjoint.py
optimistix/_custom_types.py
optimistix/_fixed_point.py
optimistix/_iterate.py
optimistix/_least_squares.py
optimistix/_minimise.py
optimistix/_misc.py
optimistix/_root_find.py
optimistix/_search.py
optimistix/_solution.py
optimistix/py.typed
optimistix/_solver/__init__.py
optimistix/_solver/backtracking.py
optimistix/_solver/best_so_far.py
optimistix/_solver/bisection.py
optimistix/_solver/dogleg.py
optimistix/_solver/fixed_point.py
optimistix/_solver/gauss_newton.py
optimistix/_solver/golden.py
optimistix/_solver/gradient_methods.py
optimistix/_solver/learning_rate.py
optimistix/_solver/levenberg_marquardt.py
optimistix/_solver/limited_memory_bfgs.py
optimistix/_solver/nelder_mead.py
optimistix/_solver/newton_chord.py
optimistix/_solver/nonlinear_cg.py
optimistix/_solver/optax.py
optimistix/_solver/quasi_newton.py
optimistix/_solver/trust_region.py
optimistix/compat/__init__.py
optimistix/compat/_impl.py
optimistix/internal/__init__.py
optimistix-0.0.11.dist-info/METADATA
optimistix-0.0.11.dist-info/WHEEL
optimistix-0.0.11.dist-info/licenses/LICENSE
optimistix-0.0.11.dist-info/RECORD
