Metadata-Version: 2.4
Name: optimistix
Version: 0.0.11
Summary: Nonlinear optimisation in JAX and Equinox.
Project-URL: repository, https://github.com/patrick-kidger/optimistix
Author-email: Jason Rader <raderjason@outlook.com>, Patrick Kidger <contact@kidger.site>
License:                                  Apache License
License-File: LICENSE
Keywords: deep-learning,equinox,jax,levenberg-marquardt,neural-networks,nonlinear-programming,numerical-optimization,optimization
Classifier: Development Status :: 3 - Alpha
Classifier: Intended Audience :: Developers
Classifier: Intended Audience :: Financial and Insurance Industry
Classifier: Intended Audience :: Information Technology
Classifier: Intended Audience :: Science/Research
Classifier: License :: OSI Approved :: Apache Software License
Classifier: Natural Language :: English
Classifier: Programming Language :: Python :: 3
Classifier: Topic :: Scientific/Engineering :: Artificial Intelligence
Classifier: Topic :: Scientific/Engineering :: Information Analysis
Classifier: Topic :: Scientific/Engineering :: Mathematics
Requires-Python: ~=3.10
Requires-Dist: equinox>=0.11.11
Requires-Dist: jax!=0.7.0,!=0.7.1,>=0.4.38
Requires-Dist: jaxtyping>=0.2.24
Requires-Dist: lineax>=0.0.6
Requires-Dist: typing-extensions>=4.5.0
Provides-Extra: dev
Requires-Dist: pre-commit; extra == 'dev'
Provides-Extra: docs
Requires-Dist: griffe==1.7.3; extra == 'docs'
Requires-Dist: hippogriffe==0.2.2; extra == 'docs'
Requires-Dist: mkdocs-include-exclude-files==0.1.0; extra == 'docs'
Requires-Dist: mkdocs-ipynb==0.1.1; extra == 'docs'
Requires-Dist: mkdocs-material==9.6.7; extra == 'docs'
Requires-Dist: mkdocs==1.6.1; extra == 'docs'
Requires-Dist: mkdocstrings-python==1.16.8; extra == 'docs'
Requires-Dist: mkdocstrings==0.28.3; extra == 'docs'
Requires-Dist: pymdown-extensions==10.14.3; extra == 'docs'
Provides-Extra: tests
Requires-Dist: beartype>=0.20.2; extra == 'tests'
Requires-Dist: diffrax>=0.7.0; extra == 'tests'
Requires-Dist: jaxlib; extra == 'tests'
Requires-Dist: optax>=0.2.4; extra == 'tests'
Requires-Dist: pytest>=8.3.5; extra == 'tests'
